rlign/__init__.py
rlign/rlign.py
rlign/utils.py
rlign-1.1.dist-info/WHEEL
rlign-1.1.dist-info/METADATA
rlign-1.1.dist-info/RECORD
